terminal_mcp_server/__init__.py
terminal_mcp_server/server.py
terminal_mcp_server-1.1.6.dist-info/licenses/LICENSE
terminal_mcp_server-1.1.6.dist-info/METADATA
terminal_mcp_server-1.1.6.dist-info/WHEEL
terminal_mcp_server-1.1.6.dist-info/entry_points.txt
terminal_mcp_server-1.1.6.dist-info/top_level.txt
terminal_mcp_server-1.1.6.dist-info/RECORD
