Metadata-Version: 2.4
Name: terminal-mcp-server
Version: 1.1.6
Summary: Smart terminal session management for AI assistants
Home-page: https://github.com/kanniganfan/terminal-mcp
Author: kanniganfan
Author-email: kanniganfan <cao673100060@gmail.com>
License: MIT
Project-URL: Homepage, https://github.com/kanniganfan/terminal-mcp
Project-URL: Repository, https://github.com/kanniganfan/terminal-mcp
Project-URL: Bug Tracker, https://github.com/kanniganfan/terminal-mcp/issues
Keywords: mcp,terminal,ai,cursor,automation,async
Classifier: Development Status :: 5 - Production/Stable
Classifier: Intended Audience :: Developers
Classifier: Topic :: Software Development :: Libraries :: Python Modules
Classifier: License :: OSI Approved :: MIT License
Classifier: Programming Language :: Python :: 3
Classifier: Programming Language :: Python :: 3.8
Classifier: Programming Language :: Python :: 3.9
Classifier: Programming Language :: Python :: 3.10
Classifier: Programming Language :: Python :: 3.11
Classifier: Programming Language :: Python :: 3.12
Requires-Python: >=3.10
License-File: LICENSE
Requires-Dist: mcp>=1.0.0
Requires-Dist: psutil>=5.9.6
Dynamic: author
Dynamic: home-page
Dynamic: license-file
Dynamic: requires-python
